gault/__init__.py
gault/accumulators.py
gault/compilers.py
gault/exceptions.py
gault/expressions.py
gault/geo.py
gault/interfaces.py
gault/managers.py
gault/mappers.py
gault/models.py
gault/pipelines.py
gault/predicates.py
gault/py.typed
gault/shapes.py
gault/sorting.py
gault/types.py
gault/utils.py
gault/window_aggregators.py
gault-0.13.0.dist-info/WHEEL
gault-0.13.0.dist-info/METADATA
gault-0.13.0.dist-info/RECORD
