Metadata-Version: 2.3
Name: gault
Version: 0.13.0
Summary: A lightweight Object Document Mapper for MongoDB
Keywords: mongodb,odm,document-mapper,orm,database
Author: Xavier Barbosa
Author-email: Xavier Barbosa <clint.northwood@gmail.com>
Classifier: Development Status :: 3 - Alpha
Classifier: Intended Audience :: Developers
Classifier: License :: OSI Approved :: MIT License
Classifier: Programming Language :: Python :: 3
Classifier: Topic :: Database
Classifier: Topic :: Software Development :: Libraries :: Python Modules
Requires-Dist: annotated-types>=0.6.0
Requires-Dist: pymongo>=4.15.4
Requires-Python: >=3.11
Project-URL: Homepage, https://github.com/johnoone/gault
Project-URL: Issues, https://github.com/johnoone/gault/issues
Project-URL: Repository, https://github.com/johnoone/gault.git
